Metadata-Version: 2.1
Name: guihandler
Version: 0.0.1
Summary: GUI for python with pygame
Home-page: UNKNOWN
Author: Milan Milenkovic
Author-email: milanmilenkovic20@gmail.com
License: MIT
Keywords: gui
Platform: UNKNOWN
Classifier: Development Status :: 5 - Production/Stable
Classifier: Intended Audience :: Education
Classifier: Operating System :: Microsoft :: Windows :: Windows 10
Classifier: License :: OSI Approved :: MIT License
Classifier: Programming Language :: Python :: 3
License-File: LICENCE.txt
